{"sweden":{"stats":[{"month":"2022-08","stats":{"count":3821,"mean":854.7084532844805,"median":864,"stddev":70.66326000337712,"max":1026,"min":351,"hist":[{"count":2,"x0":350,"x1":400},{"count":1,"x0":400,"x1":450},{"count":4,"x0":450,"x1":500},{"count":7,"x0":500,"x1":550},{"count":18,"x0":550,"x1":600},{"count":27,"x0":600,"x1":650},{"count":59,"x0":650,"x1":700},{"count":141,"x0":700,"x1":750},{"count":389,"x0":750,"x1":800},{"count":923,"x0":800,"x1":850},{"count":1275,"x0":850,"x1":900},{"count":764,"x0":900,"x1":950},{"count":202,"x0":950,"x1":1000},{"count":9,"x0":1000,"x1":1050}]},"mom":{"count":130,"mean":-0.6266862441025296,"median":-1,"stddev":0.9443126057951474,"max":0,"min":0},"yoy":null,"ytd":null},{"month":"2022-07","stats":{"count":3691,"mean":855.335139528583,"median":865,"stddev":69.71894739758197,"max":1026,"min":351,"hist":[{"count":2,"x0":350,"x1":400},{"count":1,"x0":400,"x1":450},{"count":2,"x0":450,"x1":500},{"count":8,"x0":500,"x1":550},{"count":14,"x0":550,"x1":600},{"count":24,"x0":600,"x1":650},{"count":59,"x0":650,"x1":700},{"count":129,"x0":700,"x1":750},{"count":374,"x0":750,"x1":800},{"count":887,"x0":800,"x1":850},{"count":1253,"x0":850,"x1":900},{"count":732,"x0":900,"x1":950},{"count":197,"x0":950,"x1":1000},{"count":9,"x0":1000,"x1":1050}]},"mom":{"count":211,"mean":-0.8318144944055348,"median":0,"stddev":0.1845310457587459,"max":1,"min":0},"yoy":null,"ytd":null},{"month":"2022-06","stats":{"count":3480,"mean":856.1669540229885,"median":865,"stddev":69.53441635182322,"max":1025,"min":351,"hist":[{"count":2,"x0":350,"x1":400},{"count":1,"x0":400,"x1":450},{"count":3,"x0":450,"x1":500},{"count":5,"x0":500,"x1":550},{"count":12,"x0":550,"x1":600},{"count":24,"x0":600,"x1":650},{"count":57,"x0":650,"x1":700},{"count":113,"x0":700,"x1":750},{"count":354,"x0":750,"x1":800},{"count":829,"x0":800,"x1":850},{"count":1171,"x0":850,"x1":900},{"count":716,"x0":900,"x1":950},{"count":183,"x0":950,"x1":1000},{"count":10,"x0":1000,"x1":1050}]},"mom":{"count":390,"mean":-1.9595831938399897,"median":-2,"stddev":0.5375036964698126,"max":1,"min":-25},"yoy":null,"ytd":null},{"month":"2022-05","stats":{"count":3090,"mean":858.1265372168285,"median":867,"stddev":68.99691265535341,"max":1024,"min":376,"hist":[{"count":1,"x0":350,"x1":400},{"count":1,"x0":400,"x1":450},{"count":2,"x0":450,"x1":500},{"count":2,"x0":500,"x1":550},{"count":13,"x0":550,"x1":600},{"count":16,"x0":600,"x1":650},{"count":54,"x0":650,"x1":700},{"count":97,"x0":700,"x1":750},{"count":307,"x0":750,"x1":800},{"count":717,"x0":800,"x1":850},{"count":1045,"x0":850,"x1":900},{"count":651,"x0":900,"x1":950},{"count":174,"x0":950,"x1":1000},{"count":10,"x0":1000,"x1":1050}]},"mom":{"count":349,"mean":-2.266385074306072,"median":-2,"stddev":0.28630967484224357,"max":-4,"min":-60},"yoy":null,"ytd":null},{"month":"2022-04","stats":{"count":2741,"mean":860.3929222911346,"median":869,"stddev":68.71060298051117,"max":1028,"min":436,"hist":[{"count":1,"x0":420,"x1":440},{"count":0,"x0":440,"x1":460},{"count":1,"x0":460,"x1":480},{"count":2,"x0":480,"x1":500},{"count":2,"x0":500,"x1":520},{"count":0,"x0":520,"x1":540},{"count":3,"x0":540,"x1":560},{"count":5,"x0":560,"x1":580},{"count":5,"x0":580,"x1":600},{"count":3,"x0":600,"x1":620},{"count":8,"x0":620,"x1":640},{"count":11,"x0":640,"x1":660},{"count":12,"x0":660,"x1":680},{"count":17,"x0":680,"x1":700},{"count":30,"x0":700,"x1":720},{"count":35,"x0":720,"x1":740},{"count":54,"x0":740,"x1":760},{"count":89,"x0":760,"x1":780},{"count":142,"x0":780,"x1":800},{"count":186,"x0":800,"x1":820},{"count":270,"x0":820,"x1":840},{"count":320,"x0":840,"x1":860},{"count":376,"x0":860,"x1":880},{"count":392,"x0":880,"x1":900},{"count":293,"x0":900,"x1":920},{"count":242,"x0":920,"x1":940},{"count":117,"x0":940,"x1":960},{"count":80,"x0":960,"x1":980},{"count":35,"x0":980,"x1":1000},{"count":8,"x0":1000,"x1":1020},{"count":2,"x0":1020,"x1":1040}]},"mom":{"count":342,"mean":-1.8701039698074737,"median":-2,"stddev":-0.06640779719731427,"max":-7,"min":-27},"yoy":null,"ytd":null},{"month":"2022-03","stats":{"count":2399,"mean":862.2630262609421,"median":871,"stddev":68.77701077770848,"max":1035,"min":463,"hist":[{"count":1,"x0":460,"x1":480},{"count":1,"x0":480,"x1":500},{"count":2,"x0":500,"x1":520},{"count":0,"x0":520,"x1":540},{"count":1,"x0":540,"x1":560},{"count":4,"x0":560,"x1":580},{"count":4,"x0":580,"x1":600},{"count":4,"x0":600,"x1":620},{"count":8,"x0":620,"x1":640},{"count":9,"x0":640,"x1":660},{"count":8,"x0":660,"x1":680},{"count":23,"x0":680,"x1":700},{"count":22,"x0":700,"x1":720},{"count":33,"x0":720,"x1":740},{"count":49,"x0":740,"x1":760},{"count":72,"x0":760,"x1":780},{"count":127,"x0":780,"x1":800},{"count":159,"x0":800,"x1":820},{"count":218,"x0":820,"x1":840},{"count":284,"x0":840,"x1":860},{"count":319,"x0":860,"x1":880},{"count":330,"x0":880,"x1":900},{"count":263,"x0":900,"x1":920},{"count":224,"x0":920,"x1":940},{"count":116,"x0":940,"x1":960},{"count":73,"x0":960,"x1":980},{"count":35,"x0":980,"x1":1000},{"count":8,"x0":1000,"x1":1020},{"count":2,"x0":1020,"x1":1040}]},"mom":{"count":281,"mean":-0.6467943245158949,"median":-1,"stddev":-0.8975252494548869,"max":0,"min":0},"yoy":null,"ytd":null},{"month":"2022-02","stats":{"count":2118,"mean":862.909820585458,"median":872,"stddev":69.67453602716337,"max":1035,"min":463,"hist":[{"count":1,"x0":460,"x1":480},{"count":1,"x0":480,"x1":500},{"count":2,"x0":500,"x1":520},{"count":0,"x0":520,"x1":540},{"count":1,"x0":540,"x1":560},{"count":4,"x0":560,"x1":580},{"count":3,"x0":580,"x1":600},{"count":3,"x0":600,"x1":620},{"count":7,"x0":620,"x1":640},{"count":11,"x0":640,"x1":660},{"count":9,"x0":660,"x1":680},{"count":18,"x0":680,"x1":700},{"count":19,"x0":700,"x1":720},{"count":27,"x0":720,"x1":740},{"count":44,"x0":740,"x1":760},{"count":68,"x0":760,"x1":780},{"count":103,"x0":780,"x1":800},{"count":133,"x0":800,"x1":820},{"count":200,"x0":820,"x1":840},{"count":246,"x0":840,"x1":860},{"count":276,"x0":860,"x1":880},{"count":288,"x0":880,"x1":900},{"count":239,"x0":900,"x1":920},{"count":203,"x0":920,"x1":940},{"count":103,"x0":940,"x1":960},{"count":68,"x0":960,"x1":980},{"count":31,"x0":980,"x1":1000},{"count":8,"x0":1000,"x1":1020},{"count":2,"x0":1020,"x1":1040}]},"mom":{"count":332,"mean":1.1326649303628074,"median":1,"stddev":-1.1071073974214727,"max":0,"min":0},"yoy":null,"ytd":null},{"month":"2022-01","stats":{"count":1786,"mean":861.7771556550952,"median":871,"stddev":70.78164342458484,"max":1035,"min":463,"hist":[{"count":1,"x0":460,"x1":480},{"count":1,"x0":480,"x1":500},{"count":2,"x0":500,"x1":520},{"count":0,"x0":520,"x1":540},{"count":1,"x0":540,"x1":560},{"count":4,"x0":560,"x1":580},{"count":1,"x0":580,"x1":600},{"count":3,"x0":600,"x1":620},{"count":7,"x0":620,"x1":640},{"count":11,"x0":640,"x1":660},{"count":7,"x0":660,"x1":680},{"count":15,"x0":680,"x1":700},{"count":17,"x0":700,"x1":720},{"count":24,"x0":720,"x1":740},{"count":40,"x0":740,"x1":760},{"count":60,"x0":760,"x1":780},{"count":88,"x0":780,"x1":800},{"count":113,"x0":800,"x1":820},{"count":164,"x0":820,"x1":840},{"count":208,"x0":840,"x1":860},{"count":231,"x0":860,"x1":880},{"count":250,"x0":880,"x1":900},{"count":199,"x0":900,"x1":920},{"count":164,"x0":920,"x1":940},{"count":78,"x0":940,"x1":960},{"count":60,"x0":960,"x1":980},{"count":29,"x0":980,"x1":1000},{"count":6,"x0":1000,"x1":1020},{"count":2,"x0":1020,"x1":1040}]},"mom":{"count":-1299,"mean":3.2685657037175133,"median":3,"stddev":-1.9587711775348282,"max":0,"min":436},"yoy":null,"ytd":null},{"month":"2021-12","stats":{"count":3085,"mean":858.5085899513776,"median":868,"stddev":72.74041460211967,"max":1035,"min":27,"hist":[{"count":1,"x0":0,"x1":50},{"count":0,"x0":50,"x1":100},{"count":0,"x0":100,"x1":150},{"count":1,"x0":150,"x1":200},{"count":0,"x0":200,"x1":250},{"count":0,"x0":250,"x1":300},{"count":0,"x0":300,"x1":350},{"count":0,"x0":350,"x1":400},{"count":0,"x0":400,"x1":450},{"count":4,"x0":450,"x1":500},{"count":4,"x0":500,"x1":550},{"count":15,"x0":550,"x1":600},{"count":18,"x0":600,"x1":650},{"count":46,"x0":650,"x1":700},{"count":111,"x0":700,"x1":750},{"count":300,"x0":750,"x1":800},{"count":693,"x0":800,"x1":850},{"count":1020,"x0":850,"x1":900},{"count":676,"x0":900,"x1":950},{"count":185,"x0":950,"x1":1000},{"count":11,"x0":1000,"x1":1050}]},"mom":{"count":38,"mean":-0.35291316644315884,"median":0,"stddev":-0.00823566458342384,"max":0,"min":0},"yoy":null,"ytd":null},{"month":"2021-11","stats":{"count":3047,"mean":858.8615031178208,"median":868,"stddev":72.7486502667031,"max":1035,"min":27,"hist":[{"count":1,"x0":0,"x1":50},{"count":0,"x0":50,"x1":100},{"count":0,"x0":100,"x1":150},{"count":1,"x0":150,"x1":200},{"count":0,"x0":200,"x1":250},{"count":0,"x0":250,"x1":300},{"count":0,"x0":300,"x1":350},{"count":0,"x0":350,"x1":400},{"count":0,"x0":400,"x1":450},{"count":4,"x0":450,"x1":500},{"count":4,"x0":500,"x1":550},{"count":15,"x0":550,"x1":600},{"count":18,"x0":600,"x1":650},{"count":42,"x0":650,"x1":700},{"count":108,"x0":700,"x1":750},{"count":297,"x0":750,"x1":800},{"count":679,"x0":800,"x1":850},{"count":1012,"x0":850,"x1":900},{"count":671,"x0":900,"x1":950},{"count":184,"x0":950,"x1":1000},{"count":11,"x0":1000,"x1":1050}]},"mom":{"count":56,"mean":-0.7312752171842476,"median":-1,"stddev":0.19539677811478384,"max":0,"min":0},"yoy":null,"ytd":null},{"month":"2021-10","stats":{"count":2991,"mean":859.592778335005,"median":869,"stddev":72.55325348858831,"max":1035,"min":27,"hist":[{"count":1,"x0":0,"x1":50},{"count":0,"x0":50,"x1":100},{"count":0,"x0":100,"x1":150},{"count":1,"x0":150,"x1":200},{"count":0,"x0":200,"x1":250},{"count":0,"x0":250,"x1":300},{"count":0,"x0":300,"x1":350},{"count":0,"x0":350,"x1":400},{"count":0,"x0":400,"x1":450},{"count":4,"x0":450,"x1":500},{"count":4,"x0":500,"x1":550},{"count":15,"x0":550,"x1":600},{"count":15,"x0":600,"x1":650},{"count":41,"x0":650,"x1":700},{"count":106,"x0":700,"x1":750},{"count":288,"x0":750,"x1":800},{"count":665,"x0":800,"x1":850},{"count":995,"x0":850,"x1":900},{"count":659,"x0":900,"x1":950},{"count":187,"x0":950,"x1":1000},{"count":10,"x0":1000,"x1":1050}]},"mom":{"count":123,"mean":-0.520192376292016,"median":1,"stddev":0.36143893606799793,"max":-1,"min":0},"yoy":null,"ytd":null},{"month":"2021-09","stats":{"count":2868,"mean":860.1129707112971,"median":868,"stddev":72.19181455252031,"max":1036,"min":27,"hist":[{"count":1,"x0":0,"x1":50},{"count":0,"x0":50,"x1":100},{"count":0,"x0":100,"x1":150},{"count":1,"x0":150,"x1":200},{"count":0,"x0":200,"x1":250},{"count":0,"x0":250,"x1":300},{"count":0,"x0":300,"x1":350},{"count":0,"x0":350,"x1":400},{"count":0,"x0":400,"x1":450},{"count":3,"x0":450,"x1":500},{"count":5,"x0":500,"x1":550},{"count":11,"x0":550,"x1":600},{"count":17,"x0":600,"x1":650},{"count":39,"x0":650,"x1":700},{"count":96,"x0":700,"x1":750},{"count":274,"x0":750,"x1":800},{"count":636,"x0":800,"x1":850},{"count":947,"x0":850,"x1":900},{"count":648,"x0":900,"x1":950},{"count":179,"x0":950,"x1":1000},{"count":11,"x0":1000,"x1":1050}]}}],"players":["82098","15239","27812","59092","5310","5309","25307","162405","8677","29048","96353","95050","4583","85648","59769","72302","35789","111672","30425","49449","54111","98130","101586","110699","48786","95621","135258","8560","68626","70590","101002","116137","127673","8962","25823","101609","121599","39679","3760","8937","13150","44666","107738","30427","42715","46879","68462","75209","97459","107523","123433","125137","4591","8675","50721","53993","62685","103444","53655","106139","140900","4598","53996","102051","110596","24273","34761","66744","65993","76269","81589","83353","42221","42492","78595","42493","49991","79004","82183","91187","93234","108688","8558","45412","84802","105781","130306","225417","3769","56313","97210","8955","68802","122510","122546","115601","11234","81300","85156","92074","66505","81376","91175","130229","3422","48679","60171","74551","82156","118371","135272","176312","209199","8557","73664","97975","105925","121954","38490","43930","64982","95395","95558","43270","102050","104453","120680","122024","97410","113155","130625","13750","46650","53883","59097","76246","77677","83873","121071","132751","173250","177014","206859","15240","68519","157282","178903","191007","49474","58368","61281","98528","135125","36404","38988","85206","103608","138352","162114","182331","207198","8933","29700","53201","59771","84423","88127","179111","198054","226457","4573","32927","43760","47361","57981","93455","117827","128374","180783","8958","12089","24960","103830","111064","119442","120179","142574","211265","8561","29055","53400","85726","94146","3438","92996","124218","170805","8659","34670","116727","178714","3754","30565","37031","50206","53394","66117","83875","138539","146589","156101","73304","115420","213953","82000","110794","190064","4567","8908","78593","78871","85709","97860","120872","130963","213854","29697","50112","74802","78592","85121","91967","123674","131483","149817","30937","36679","49450","53399","60170","63533","92342","124881","188629","17315","47829","53891","74340","95072","108833","122596","182156","203896","66399","83428","96364","119025","125741","140678","151813","8973","42727","43456","50187","79643","123443","162717","222466","43245","49447","82215","91177","109780","118725","124558","173470","177342","205582","205790","217524","8785","38491","39006","52409","91281","108217","117674","123218","126349","147367","167012","176735","213377","8664","68532","74925","77190","103240","119628","137671","142616","175160","184856","197928","202384","223956","226208","74983","75014","96163","130180","165175","8585","30002","34421","99261","101365","103696","109814","111840","135674","180857","43928","85725","111693","125102","131166","137757","141052","158390","189209","189502","41732","85202","85713","97621","107057","116975","142282","155924","157038","34671","39418","59178","59982","87125","91013","93296","97002","103431","108636","128233","131023","141958","202849","222995","3415","4576","8965","44530","51181","55238","55842","63521","77419","82100","94751","121215","131365","180385","190268","219357","35321","82516","120755","122937","124077","134987","138217","140092","188599","209018","222044","42525","43460","58861","66269","108041","111799","122080","122082","125027","148597","149402","158703","168401","177733","186436","211481","8957","35540","42412","102059","105240","115590","132307","135633","147441","171359","227843","8910","46940","66509","75180","94483","119014","125028","131241","137991","149244","49990","74796","75086","85509","123530","126164","136527","137988","138985","142393","155743","180303","180325","190264","77710","82650","101727","103241","111576","116164","139779","140482","153735","167107","180030","184130","185860","186619","196153","46651","46729","57672","62684","88603","91110","96280","106944","115355","121660","122787","127926","140471","142468","148627","159979","172535","189893","52639","58188","67666","76037","81338","91860","94389","97075","107862","127484","135652","137145","142920","173542","192079","205063","207907","65991","74926","89702","96029","109284","125302","130391","149455","151868","175897","214335","67913","76411","104429","106832","125287","127705","135631","140177","140668","156913","215390","3436","8662","50011","50428","73485","74588","76158","104833","105275","111524","129782","129864","140074","143632","149319","180215","189455","205583","213805","214873","219816","222416","8931","38492","46913","65978","73122","79656","82080","121658","125508","135568","147003","160177","173373","175075","180095","182042","185995","202919","8690","30302","38638","51182","98582","104173","107143","116533","118434","118492","119843","130654","142489","145501","151652","164324","169934","176145","180029","180315","180651","181881","184114","185604","189270","204694","8938","87508","93810","111533","123334","135821","136181","140590","140675","140772","144490","152857","157270","181233","186691","188844","8600","50186","51696","61428","77255","117755","124158","124913","146024","150746","160982","165554","173530","187171","218666","36405","45160","59091","59179","73631","100700","103829","110588","122402","132134","160124","174645","176020","176541","186471","215387","3429","5308","37029","53813","74473","91011","106469","108173","109897","171140","173698","180962","215761","39767","51856","57361","72718","82942","107857","110887","116704","121299","123136","131575","137598","142059","142325","142405","162058","164844","175380","176204","188063","188668","189658","206706","207237","3759","38473","53147","75234","77286","92358","95339","95764","116820","119626","121506","121981","124349","127956","131521","134941","136331","178326","190299","190869","194415","227358","29051","38474","44785","47237","48787","50840","65355","82812","84644","102159","118315","119676","119848","120469","122392","143089","150996","161085","183575","186674","192815","224540","8682","39175","50072","65147","85347","92506","103740","110608","120420","121317","125071","126925","138882","153917","171870","173079","190584","193682","204340","221107","23704","48165","105886","110489","111785","121659","127442","128126","131544","138614","142406","153896","171030","175163","193269","204725","207032","212788","5304","8963","33118","33386","53546","82649","96132","102748","103609","110381","130908","142540","160060","164467","186446","186513","188983","189725","203363","224012","8663","8934","101528","103242","116897","118826","120200","120560","120793","121142","130046","141505","143087","146488","176994","182634","183012","185052","209924","3758","8666","8972","93661","103179","131122","131790","133921","134056","166314","166504","179808","183765","184559","185907","187296","188594","189959","219363","222100","3767","29699","46880","81356","84231","90372","100242","105884","127954","131751","142707","144571","180160","186512","187177","195796","218127","94300","95613","112138","148027","159857","173457","173575","175219","182211","188345","188414","189304","209498","213999","214874","218523","8596","54614","95338","103194","108637","108715","109131","111783","120114","124997","128023","130193","134161","137869","180323","183417","187144","189271","202401","210240","216569","219008","224114","52316","68052","82099","92058","121726","123652","141756","147476","174548","212628","219705","222609","223214","3421","8971","39678","42494","53547","55097","61122","77903","90308","92861","98392","98967","130114","130183","139980","145629","146965","176349","178976","179115","181287","189680","191008","204818","219221","8670","66511","66917","85204","97489","104488","117858","123629","127980","134899","135555","140250","140775","142481","157444","171112","173301","173711","173716","174731","177393","180730","181197","187106","191185","215636","73841","74651","80216","85229","86359","106073","109281","113195","116051","122347","124189","125839","132693","133749","145276","145899","146057","160917","161998","169910","172365","175329","175571","181297","183239","188473","214236","215616","224808","8959","25235","77981","91153","101761","108538","119133","122379","122776","124457","134549","135704","137175","139286","139369","140929","141275","142297","146868","157453","171012","173038","177391","180515","181175","186071","191793","228679","185057","34065","52060","98543","107811","123163","123411","126564","130396","131678","134419","136557","161220","161595","177251","177478","180108","180277","204336","209081","212680","215458","47035","53064","54244","57985","75216","77357","79222","103717","104136","106431","108475","116818","123772","128421","130397","136680","140877","169273","170822","181011","186201","190255","206475","215868","139387","8575","51567","64021","66298","68995","72607","83902","93459","104335","108737","111694","131213","143453","144098","146576","147633","150021","164488","172196","172521","178093","178971","183117","196896","214354","216946","217803","225663","8975","31802","49448","80340","84492","89483","106831","108043","113576","114387","114989","121072","121764","122218","124458","130543","149047","156378","159852","166426","170718","172177","181877","185053","191540","201521","204345","209700","210840","214639","53148","77175","77535","122023","125303","126168","127684","129438","130015","160653","173189","181324","186588","190364","200722","200966","208800","208966","218976","3761","43269","70899","87273","88232","99501","102967","107145","109118","109990","124839","141549","147417","156258","172831","173435","176200","181820","201757","38494","65979","73301","85364","107131","109649","117411","120333","122042","123770","125230","139201","140251","141171","144219","145522","178097","181315","181350","181873","182277","187136","187760","198157","202532","204964","204993","216624","8577","8586","101135","102030","110834","118557","120966","124468","134303","134429","134807","137404","160065","165031","169094","215459","219442","221149","15916","53204","78792","102539","103158","113500","116043","119993","121143","127129","130916","131524","134133","135689","136748","157239","157342","160071","165327","172693","174428","177072","179640","180074","184122","187261","221740","227439","121554","8686","57644","70595","77547","80510","84276","106946","114927","119564","124734","131424","135678","140176","140691","146132","161221","164309","165328","170821","172106","180858","180914","196661","203485","204847","209343","213370","215633","219799","8925","35097","39677","89281","91618","102857","103940","116104","120803","122087","124676","124785","131124","135157","137171","145524","150349","152978","156886","170777","174283","176702","205940","207859","209556","215463","217512","218408","224451","30939","36545","85205","91123","108503","118780","120115","129323","131700","139231","145273","164374","165329","171022","181582","182029","182224","182607","184476","184819","187890","193600","203976","204843","205453","214453","215031","217855","218586","77385","96628","111153","121663","122484","122580","123937","135129","136007","138946","139371","140661","157399","165045","167944","173535","176285","176322","178972","180607","184758","202718","38495","60168","69894","75970","118305","126750","128671","129107","131276","132495","145340","146853","160473","176569","185307","185731","186481","188413","200721","203015","205722","208524","213212","216400","222127","224348","48883","52866","58187","90213","101610","107525","107764","125743","125847","135390","145606","171918","173346","173892","175001","179402","180299","180304","181171","183617","185853","189086","198751","205535","206070","217544","217646","218210","48884","50329","53401","60954","108874","119629","120231","122875","140438","148668","149143","150035","160379","165774","166659","174046","175027","179476","179679","180383","181056","184180","184595","187473","190256","202066","204844","206118","208300","208527","213322","223642","81778","84295","120418","123771","124578","129991","131610","132267","134305","134828","142322","146423","168133","171292","173537","176050","182011","185366","186924","193023","194497","215315","216266","219233","70280","72337","108228","119318","121609","130205","134226","135675","142386","142692","155095","161593","171899","174221","175156","181918","182271","182368","184974","193236","193978","200980","204600","208883","209267","219798","221390","3752","71710","76929","93603","101810","103190","103460","110443","134967","137983","138890","141380","141586","178109","179775","180721","181237","182254","186986","187881","192380","202889","222013","76436","84148","85570","109523","116207","123222","127658","141186","153578","172578","175009","176211","176439","178474","181004","187543","195397","200865","203345","205225","218471","109612","59472","63532","65149","81656","103027","107285","127111","130736","139121","148822","151814","160175","164352","168317","174541","175783","178060","180658","181352","181920","184604","191682","205778","210298","218075","224082","1582","3418","64389","67778","93045","113572","126191","126968","129339","135616","139424","144953","161434","164472","181008","181236","182184","182643","182797","187226","188803","188904","199308","200625","203347","204737","209198","212772","218723","219975","220238","221676","111790","34954","60040","123119","135754","139652","141369","147725","161458","169218","173425","176056","178262","187495","188978","195140","198119","204411","204814","205076","206217","211944","35052","40048","42417","43459","85890","107580","108018","115574","122031","127233","160078","170599","171138","171507","173085","176045","180327","180650","181121","191555","202426","205227","205934","206114","211301","212848","214405","215920","216276","221860","223955","39007","56708","95581","116896","116969","121423","122188","123298","126229","127085","127237","128363","129522","146581","160067","166245","167582","172692","174729","179367","184651","191495","196319","202410","204744","205052","205210","206152","209089","212005","213144","213340","215072","225472","4574","13175","101587","109656","116651","117754","118980","126240","137219","137966","149024","149450","149774","151117","155608","163314","168004","169802","171107","187684","199887","209225","209755","215611","217212","219181","224116","57829","118516","128768","129135","137911","173944","183375","189919","195867","197985","206214","206275","211507","215312","215789","219235","223157","225644","35774","44936","97595","123975","135457","135823","146427","148604","148623","151587","155417","162365","171207","176272","179376","181296","190282","203061","203647","209156","211260","213395","219029","48164","51388","76644","108384","129757","134465","135858","135962","137192","144667","144899","145486","158127","164738","166230","176291","184569","186848","187512","188515","202008","203373","204113","214402","215949","216022","219907","221392","222326","38478","77982","107761","121144","124318","145439","145520","148508","161759","164773","165176","166607","168487","173344","175997","176571","180720","186452","186699","190325","202702","206072","209838","213463","214775","215758","217813","219065","221091","221901","224128","4560","57373","74774","91081","92006","103188","109779","124837","131216","135697","135980","168099","173703","176172","183769","185083","186072","188260","190342","194990","197514","198579","200923","201752","210592","214416","215237","221104","142225","8966","51855","64546","92201","95922","108470","120649","128650","140077","140439","142856","160911","170719","173000","177483","184861","184882","186908","187097","187590","189739","193879","201221","203569","204196","213271","213789","220957","227402","18750","179873","73529","84455","116728","124863","131174","131837","133696","134627","136100","136184","138125","140589","150705","161834","162267","168224","174107","177943","178975","182878","183723","184551","187061","187653","193940","205371","206998","213702","213917","217385","220727","221294","36809","58694","110243","119017","122027","133867","139565","140435","140811","144473","149650","152051","157353","165242","165436","173001","173538","174862","177655","179127","181695","183435","189152","189290","194400","197773","206594","209221","213200","216200","111514","75285","76754","80209","103822","120881","124375","125806","126001","127674","134546","136285","136477","142094","145484","173952","174745","176006","178606","180230","185056","205207","210755","216317","218051","219840","223648","229136","155026","64703","81403","88231","122516","124844","131758","138161","139469","145242","153357","172075","175162","180788","189894","190414","190602","199363","209076","213376","213976","219050","219062","220794","70901","76337","111602","117948","122579","139203","144351","145272","165332","172540","174396","175427","192462","195735","199092","200252","201451","201779","208861","217370","218256","219980","221537","221622","223221","227170","102358","107931","122214","122648","124504","139718","145048","155421","157706","163274","163358","176298","176600","180757","182803","194440","202745","204966","210234","213779","227762","8599","124140","124430","132766","133740","135571","136685","161112","162681","174310","178968","187383","188867","196737","197988","202863","203062","209419","210734","210995","213326","213461","216288","218206","219586","221990","227743","56707","136348","170717","170806","171121","173037","173120","177596","179201","180886","184567","186256","186903","188525","201250","206480","215165","219346","108925","119286","131221","135737","139780","161219","165764","175388","175725","179438","181583","185051","187979","192757","195909","198666","203857","209357","216263","218710","222697","223958","224412","226225","226242","88299","123758","127682","130767","140807","164619","172262","174421","180777","181700","184979","189467","190283","193622","196124","210588","214073","216210","217502","218046","224471","82641","99530","106897","132752","137905","139112","140735","157433","171109","171303","173256","178325","180012","180615","186912","205600","206406","209021","213388","215765","222695","224934","121240","130014","47918","75611","108424","119460","142411","159985","176444","177066","180779","182272","186791","187387","189661","193177","194866","198272","206119","206221","211309","211754","214789","216035","218134","102567","103041","129948","136606","140592","151062","151170","156090","165917","171293","173265","175811","185527","189751","190987","202242","202378","213855","218100","219060","221022","91819","95092","125039","135770","146696","149643","167048","169535","172263","174228","176149","176154","184695","184984","203351","206213","214446","221133","85203","112174","137747","140659","149583","149797","161310","162016","170630","172703","173168","174136","177476","178046","179643","180734","180930","185376","186166","189597","193535","195316","203189","205117","205572","206925","209262","226615","107926","107989","114522","119232","127481","135638","169483","174486","175410","187977","204855","206708","218473","219824","226934","63165","63345","93601","107174","42832","80398","81508","85712","93971","94891","113571","131438","138379","147364","152855","171395","172804","173975","180792","182709","184862","202576","207153","208984","214092","217551","218905","219313","111699","79934","99483","103178","108108","119730","121097","132155","145832","161997","162484","166131","170902","176692","182030","182628","187382","191527","192084","200855","204931","212192","212576","217035","220800","118072","120767","121889","136147","142568","158216","167730","168576","171299","180518","183896","185983","192195","200944","203845","204687","204956","206137","206241","208526","209338","209655","213353","213618","215954","217283","220199","220962","107428","131743","142647","150344","152311","170899","172995","176697","180007","186953","207228","219704","228319","57375","76159","131873","132191","139924","146861","155612","161217","162307","172906","175565","179573","180860","181302","188901","192011","203492","205999","212842","213490","216796","74985","79003","102610","108569","117071","127564","161355","166138","167244","169280","171294","171404","175052","175308","176287","177005","179563","181284","181584","182498","183224","200754","201449","203053","204870","206926","212474","213692","215452","217025","228954","67755","112945","121141","121816","141215","142495","142940","151693","171116","174916","175408","176553","177933","179871","186795","189476","189547","189896","205593","209024","209511","211998","213793","217109","219069","219945","227742","3419","31701","48860","67190","84193","103611","107379","107858","122079","148651","155294","171298","173003","175231","176067","177807","178737","180181","181247","185091","188914","191802","214088","214454","219835","220338","223299","91382","116247","122869","124429","124928","128111","138765","142850","145480","172217","173050","175188","176986","181579","181884","184692","189016","189412","192283","201220","205346","207436","216274","227091","109679","122522","127871","134639","135215","142994","144242","147686","161239","167767","179686","183696","187019","187223","189771","194682","198550","200245","203376","209916","219913","182450","122255","133862","148665","152444","170980","176696","186303","186896","186971","190956","204527","212964","213061","214301","214423","215466","217131","223199","226432","137054","118370","119960","121961","144257","145426","147723","162901","171328","171378","173700","176151","180726","186684","193585","206077","209210","213616","218469","97462","108648","126748","129365","130760","131835","133175","147380","150122","160385","161589","166457","167348","177783","180010","189449","193979","207344","210996","212505","213785","217441","54615","95670","104661","124722","135824","146491","161168","165369","171187","177471","180879","182017","182453","184696","199882","200247","204973","205292","206130","207461","212066","214135","215046","216921","218774","220523","224744","226470","226844","85641","100876","126224","139464","140078","149973","161581","165731","173630","175510","178654","180645","182132","197731","198116","204811","206577","211251","215456","217549","218052","218993","219316","220547","227607","228420","228886","3432","107812","121922","157900","169725","171573","174771","180423","189749","217365","218883","220855","224115","118679","134936","138220","146532","148052","176283","181316","181377","181395","185714","186995","189450","189727","190557","194401","194836","206615","206923","210428","210690","215754","216787","216910","217105","225310","227351","106355","112109","151056","161363","163266","170929","174398","176146","181691","191186","202726","204935","205555","205993","211643","212112","213925","218585","219434","220507","89044","103610","107825","130113","139377","147500","148532","156010","156033","161993","166525","172520","173263","173383","178978","180851","182456","186525","188990","193715","199088","200627","202580","211883","211894","217064","222236","121837","140368","140442","146989","157054","173696","181507","182256","188368","188683","194849","198602","206510","218049","218053","218073","223951","206376","38476","76338","103862","122294","128766","140381","142337","148015","159344","161347","169073","170549","176193","180234","180324","181239","181622","181723","181933","186597","193233","199307","205826","207439","210847","218244","219740","223347","224523","225891","179106","102139","131859","135573","136894","142683","150140","159699","173406","176096","182282","184419","187174","187794","194502","194841","201528","221261","221532","225434","227647","228417","45159","107860","138081","99121","161992","168031","175018","177835","183450","186257","188422","188675","188991","207066","208471","212513","215153","215323","222439","47917","103833","104319","107273","110934","122578","125408","130655","145218","172349","172738","172751","173185","176695","182379","188194","201687","202534","205461","208270","209147","210675","175392","72832","128679","132069","154631","179966","188520","202851","206382","214242","217210","219374","221908","224746","104318","110797","111922","121790","153710","155816","168304","170823","171320","180862","181125","191797","205995","210069","221447","222903","223763","225792","97460","123960","126452","131841","138723","172351","172885","178515","180279","185327","187159","188228","203259","209051","220347","46881","120848","123153","130458","138962","144410","150219","173005","184759","187319","190582","194787","195151","201575","204954","217785","223018","156259","94825","122261","123116","145236","149462","171385","180612","186598","188436","191544","202376","214310","218663","219691","228430","180210","1187","103947","155851","160084","172914","175660","196063","197649","206784","216771","219219","221384","222443","227863","53892","138805","140616","150024","161208","164755","173275","182564","188513","201665","213821","216420","218763","220439","221867","125495","97335","124466","149307","171869","181372","182868","185080","203159","203480","204979","212480","213399","216286","217498","217947","217962","218204","137990","47148","57828","98755","103239","135782","164484","176263","177278","184654","184772","184999","185408","185851","190586","194544","195977","198117","204810","211463","211732","217570","219066","226763","228491","111490","112946","140656","177350","187028","199408","199520","201468","211817","103955","142290","145498","151124","166857","175303","186535","186590","188728","190604","207600","209558","211902","218995","219494","225385","226097","66512","109733","140456","152258","160935","174609","187234","193847","194927","200239","213458","218583","95341","111996","170598","182334","204186","205812","214149","214269","220144","158379","119231","119668","121661","143361","165533","168398","174135","175064","178439","186595","189610","201507","203645","205534","214074","216034","216064","216281","26585","35581","124283","171023","181261","188435","190610","193674","195228","198310","212397","213981","215184","215462","215877","218123","76066","3765","40047","80952","166101","183902","191526","201858","205055","207304","210741","211620","216859","216867","218772","65479","100515","131757","138218","142695","151200","158481","167610","171327","173706","175333","179269","185287","189089","191093","205111","216865","222699","224008","228585","113409","140910","149415","161308","168275","173899","174152","176040","178894","178908","185174","188980","201850","208405","218768","219660","75041","98715","127680","150114","173905","178475","183826","188548","192275","197668","215180","143439","210542","212681","135557","139917","169304","171357","180061","183313","184008","189682","191196","192236","196819","199881","203836","211875","216626","220226","222459","226233","185373","125512","139417","165201","171331","171347","177352","182336","194981","195313","201685","211453","216387","220647","223215","143295","25847","172896","175505","181015","182898","186836","196820","197987","202218","205059","213918","217555","220101","131874","172392","175805","178502","182899","183456","206607","215309","219575","221232","222307","224721","179433","78855","120706","138210","164469","171307","180737","187378","194403","220864","203676","134310","135471","138551","140195","142176","149923","160190","182589","183217","190595","215640","218773","145975","162264","99518","128341","131435","145512","170028","176059","182714","192730","205584","206732","209244","209560","213218","218992","188271","127137","145510","162668","173443","194397","209653","211101","212835","128655","50111","130172","131848","157975","181741","187373","187530","187697","64704","108946","129137","137501","173702","187239","188720","201306","203928","208842","216699","218481","221381","139385","215919","61247","121355","140070","162670","165895","166485","171136","221153","225474","226710","226829","174285","216919","132180","161859","172185","176293","176484","177164","181718","187006","204998","211026","213923","219829","190230","175499","184706","185379","193183","202306","215764","225391","124315","150348","151671","169756","173812","183544","185189","205016","209553","154082","160961","171717","176206","179313","188267","190112","202052","204930","210307","139859","222711","96990","143166","157319","186796","196499","201496","203236","213324","223190","57984","139954","205978","175098","187475","188591","191064","201737","214623","221339","56709","59093","116290","129518","176566","181619","183791","188149","201859","210311","215220","218063","134935","214779","157144","163317","176910","193960","216587","223475","135262","146181","170770","172898","146489","167580","173768","178438","181817","193422","226708","227409","228692","127172","127372","131821","151655","184684","187304","187842","189639","201656","203367","217062","220959","192784","193134","202069","215872","220285","221340","227872","206484","76668","135974","147610","159602","169772","173446","181810","201193","222863","142052","181856","114823","169917","176346","195141","214422","215770","223198","107746","136855","141656","155418","176980","182691","217111","222300","225226","131910","189728","206487","206521","222034","163141","181854","184656","164750","169774","172668","174576","190459","206337","209270","209715","214584","225318","225441","97497","108454","200618","209250","216543","222968","219437","219492","110416","122022","124791","140909","172858","181126","210728","216443","217433","219368","221351","109120","205586","174739","180611","188723","210969","219168","227501","182257","219496","145224","145495","178041","203927","205061","96668","125454","179133","187864","204541","209509","215651","134060","174061","184689","189154","190253","209739","213267","174643","188442","78156","152011","170417","177148","184323","189233","181232","227450","177370","178509","189011","204235","204959","205325","208805","213152","224007","126539","161467","191881","204972","214514","218921","220217","133538","197921","211604","223640","158214","38475","168217","173364","177011","194548","198287","202205","212692","221668","221851","223463","225482","227969","139384","166608","181823","182455","186906","200248","213811","187513","218344","108333","157434","192725","209676","209949","152705","187238","151121","173062","187885","205585","212400","224413","211517","151659","177174","210155","126060","180071","182583","196021","213620","226252","18800","189646","174927","177369","209031","217957","221345","206506","213623","218404","135534","181457","186900","195152","195341","213846","214408","141582","176489","188440","77977","136904","154818","176617","192461","198167","131815","186681","90104","107488","206127","173374","178483","219453","148003","185300","217194","191798","8909","42575","155546","171758","219230","211804","219696","226047","138717","186616","179304","106291","177166","186985","214003","218243","218251","220381","180068","188300","183373","221999","151165","104147","213915","220509","123237","143455","200249","200720","211727","225439","210546","184118","212239","202018","171776","201707","213826","220515","220851","171191","214084","185575","187573","147414","173417","186336","219697","134250","158165","218996","174058","185199","202881","4580","195222","200455","228675","160073","184701","188427","204412","177828","183114","217237","190585","205581","218909","224191","225101","212672","111902","211143","221869","217967","219505","144241","184123","217688","219493","168282","188783","217224","176564","211274","217536","226622","209954","188526","204256","184413","220960","130081","217243","172510","178527","225493","216895","189699","193539","195124","226099","205136","219242","227909","160782","206128","173424","172355","203413","215319","227057","124979","143846","172548","161050","162056","205057","109730","183543","202379","203402","153561","206476","225031","222184","204257","206121","214427","142948","227150","47646","189367","215047","206132","196364","160892","142302","192385","218652","183478","208879","216930","156009","174872","195319","196505","211247","186454","191800","215596","193572","154819","93970","181578","136530","184921","187823","188937","94092","210761","226991","224311","221499","217671","219002","163276","213157","221643","224400","191621","190550","192543","203926","220115","228798","149688","218385","223957","79221","188742","178670","194971","198577","224651","189640","214881","189477","194974","227609","146854","212688","188590","172175","218202","206710","214094","107634","113901","128869","200486","173004","178858","192295","213621","8939","220761","221540","206580","217388","124075","205321","143515","216406","155533","129636","218476","186334","191712","192922","175467","223298","182382","66270","206057","172350","173014","207887","190549","220648","219072","196120","210986","151973","210568","205126","227427","174229","183919","216772","132711","171015","210710","222343","162040","214899","178893","146416","229208","170708","204750","138160","219184","211877","221269","118983","219573","205302","135448","180011","184827","215385","224238","150644","205226","222234","191547","202759","185590","207348","185868","222620","189308","222251","188263","123346","180019","157115","216314","133919","219310","208444","185589","179378","226900","221895","141581","98607","123699","186031","213316","119565","179058","218484","227163","214941","210983","189165","218199"]}}