{"sweden":{"stats":[{"month":"2023-03","stats":{"count":2862,"mean":857.5296995108316,"median":865,"stddev":69.86654688050245,"max":1026,"min":24,"hist":[{"count":1,"x0":0,"x1":50},{"count":0,"x0":50,"x1":100},{"count":0,"x0":100,"x1":150},{"count":0,"x0":150,"x1":200},{"count":0,"x0":200,"x1":250},{"count":0,"x0":250,"x1":300},{"count":0,"x0":300,"x1":350},{"count":1,"x0":350,"x1":400},{"count":0,"x0":400,"x1":450},{"count":1,"x0":450,"x1":500},{"count":2,"x0":500,"x1":550},{"count":8,"x0":550,"x1":600},{"count":19,"x0":600,"x1":650},{"count":43,"x0":650,"x1":700},{"count":105,"x0":700,"x1":750},{"count":291,"x0":750,"x1":800},{"count":677,"x0":800,"x1":850},{"count":930,"x0":850,"x1":900},{"count":602,"x0":900,"x1":950},{"count":173,"x0":950,"x1":1000},{"count":9,"x0":1000,"x1":1050}]},"mom":{"count":251,"mean":-1.8973399376556017,"median":-2,"stddev":-0.13076348806637839,"max":0,"min":0},"yoy":null,"ytd":{"count":1076,"mean":-4.247456144263538,"median":-6,"stddev":-0.9150965440823882,"max":-9,"min":-439}},{"month":"2023-02","stats":{"count":2611,"mean":859.4270394484872,"median":867,"stddev":69.99731036856883,"max":1026,"min":24,"hist":[{"count":1,"x0":0,"x1":50},{"count":0,"x0":50,"x1":100},{"count":0,"x0":100,"x1":150},{"count":0,"x0":150,"x1":200},{"count":0,"x0":200,"x1":250},{"count":0,"x0":250,"x1":300},{"count":0,"x0":300,"x1":350},{"count":1,"x0":350,"x1":400},{"count":0,"x0":400,"x1":450},{"count":1,"x0":450,"x1":500},{"count":1,"x0":500,"x1":550},{"count":8,"x0":550,"x1":600},{"count":15,"x0":600,"x1":650},{"count":38,"x0":650,"x1":700},{"count":97,"x0":700,"x1":750},{"count":250,"x0":750,"x1":800},{"count":598,"x0":800,"x1":850},{"count":857,"x0":850,"x1":900},{"count":562,"x0":900,"x1":950},{"count":173,"x0":950,"x1":1000},{"count":9,"x0":1000,"x1":1050}]},"mom":{"count":433,"mean":0.8264884842999436,"median":1,"stddev":-0.1949628862096091,"max":0,"min":0},"yoy":null,"ytd":{"count":825,"mean":-2.350116206607936,"median":-4,"stddev":-0.7843330560160098,"max":-9,"min":-439}},{"month":"2023-01","stats":{"count":2178,"mean":858.6005509641873,"median":866,"stddev":70.19227325477844,"max":1026,"min":24,"hist":[{"count":1,"x0":0,"x1":50},{"count":0,"x0":50,"x1":100},{"count":0,"x0":100,"x1":150},{"count":0,"x0":150,"x1":200},{"count":0,"x0":200,"x1":250},{"count":0,"x0":250,"x1":300},{"count":0,"x0":300,"x1":350},{"count":1,"x0":350,"x1":400},{"count":0,"x0":400,"x1":450},{"count":1,"x0":450,"x1":500},{"count":1,"x0":500,"x1":550},{"count":6,"x0":550,"x1":600},{"count":12,"x0":600,"x1":650},{"count":30,"x0":650,"x1":700},{"count":80,"x0":700,"x1":750},{"count":221,"x0":750,"x1":800},{"count":505,"x0":800,"x1":850},{"count":704,"x0":850,"x1":900},{"count":467,"x0":900,"x1":950},{"count":140,"x0":950,"x1":1000},{"count":9,"x0":1000,"x1":1050}]},"mom":{"count":-1970,"mean":4.828853760715674,"median":3,"stddev":-0.8701471809219044,"max":0,"min":0},"yoy":null,"ytd":{"count":392,"mean":-3.1766046909078796,"median":-5,"stddev":-0.5893701698064007,"max":-9,"min":-439}},{"month":"2022-12","stats":{"count":4148,"mean":853.7716972034716,"median":863,"stddev":71.06242043570035,"max":1026,"min":24,"hist":[{"count":1,"x0":0,"x1":50},{"count":0,"x0":50,"x1":100},{"count":0,"x0":100,"x1":150},{"count":0,"x0":150,"x1":200},{"count":0,"x0":200,"x1":250},{"count":0,"x0":250,"x1":300},{"count":0,"x0":300,"x1":350},{"count":2,"x0":350,"x1":400},{"count":1,"x0":400,"x1":450},{"count":3,"x0":450,"x1":500},{"count":7,"x0":500,"x1":550},{"count":16,"x0":550,"x1":600},{"count":32,"x0":600,"x1":650},{"count":70,"x0":650,"x1":700},{"count":147,"x0":700,"x1":750},{"count":435,"x0":750,"x1":800},{"count":1007,"x0":800,"x1":850},{"count":1368,"x0":850,"x1":900},{"count":842,"x0":900,"x1":950},{"count":207,"x0":950,"x1":1000},{"count":10,"x0":1000,"x1":1050}]},"mom":{"count":36,"mean":0.1389151023042814,"median":0,"stddev":-0.2915423900375771,"max":0,"min":0},"yoy":{"count":1063,"mean":-4.73689274790604,"median":-5,"stddev":-1.6779941664193245,"max":-9,"min":-3},"ytd":null},{"month":"2022-11","stats":{"count":4112,"mean":853.6327821011673,"median":863,"stddev":71.35396282573792,"max":1026,"min":24,"hist":[{"count":1,"x0":0,"x1":50},{"count":0,"x0":50,"x1":100},{"count":0,"x0":100,"x1":150},{"count":0,"x0":150,"x1":200},{"count":0,"x0":200,"x1":250},{"count":0,"x0":250,"x1":300},{"count":0,"x0":300,"x1":350},{"count":2,"x0":350,"x1":400},{"count":1,"x0":400,"x1":450},{"count":3,"x0":450,"x1":500},{"count":7,"x0":500,"x1":550},{"count":16,"x0":550,"x1":600},{"count":32,"x0":600,"x1":650},{"count":71,"x0":650,"x1":700},{"count":146,"x0":700,"x1":750},{"count":433,"x0":750,"x1":800},{"count":999,"x0":800,"x1":850},{"count":1362,"x0":850,"x1":900},{"count":823,"x0":900,"x1":950},{"count":206,"x0":950,"x1":1000},{"count":10,"x0":1000,"x1":1050}]},"mom":{"count":33,"mean":-0.17354297850909006,"median":0,"stddev":1.1858653622486628,"max":0,"min":-327},"yoy":{"count":1065,"mean":-5.2287210166534805,"median":-5,"stddev":-1.3946874409651713,"max":-9,"min":-3},"ytd":null},{"month":"2022-10","stats":{"count":4079,"mean":853.8063250796764,"median":863,"stddev":70.16809746348926,"max":1026,"min":351,"hist":[{"count":2,"x0":350,"x1":400},{"count":1,"x0":400,"x1":450},{"count":3,"x0":450,"x1":500},{"count":7,"x0":500,"x1":550},{"count":16,"x0":550,"x1":600},{"count":31,"x0":600,"x1":650},{"count":69,"x0":650,"x1":700},{"count":145,"x0":700,"x1":750},{"count":430,"x0":750,"x1":800},{"count":992,"x0":800,"x1":850},{"count":1357,"x0":850,"x1":900},{"count":812,"x0":900,"x1":950},{"count":204,"x0":950,"x1":1000},{"count":10,"x0":1000,"x1":1050}]},"mom":{"count":86,"mean":-0.01761681864570619,"median":0,"stddev":-0.40689640734574084,"max":4,"min":0},"yoy":{"count":1088,"mean":-5.786453255328638,"median":-6,"stddev":-2.3851560250990502,"max":-9,"min":324},"ytd":null},{"month":"2022-09","stats":{"count":3993,"mean":853.8239418983221,"median":863,"stddev":70.574993870835,"max":1022,"min":351,"hist":[{"count":2,"x0":350,"x1":400},{"count":1,"x0":400,"x1":450},{"count":4,"x0":450,"x1":500},{"count":7,"x0":500,"x1":550},{"count":16,"x0":550,"x1":600},{"count":32,"x0":600,"x1":650},{"count":65,"x0":650,"x1":700},{"count":146,"x0":700,"x1":750},{"count":425,"x0":750,"x1":800},{"count":957,"x0":800,"x1":850},{"count":1333,"x0":850,"x1":900},{"count":794,"x0":900,"x1":950},{"count":201,"x0":950,"x1":1000},{"count":10,"x0":1000,"x1":1050}]},"mom":{"count":172,"mean":-0.8845113861583513,"median":-1,"stddev":-0.08826613254211679,"max":-4,"min":0},"yoy":null,"ytd":null},{"month":"2022-08","stats":{"count":3821,"mean":854.7084532844805,"median":864,"stddev":70.66326000337712,"max":1026,"min":351,"hist":[{"count":2,"x0":350,"x1":400},{"count":1,"x0":400,"x1":450},{"count":4,"x0":450,"x1":500},{"count":7,"x0":500,"x1":550},{"count":18,"x0":550,"x1":600},{"count":27,"x0":600,"x1":650},{"count":59,"x0":650,"x1":700},{"count":141,"x0":700,"x1":750},{"count":389,"x0":750,"x1":800},{"count":923,"x0":800,"x1":850},{"count":1275,"x0":850,"x1":900},{"count":764,"x0":900,"x1":950},{"count":202,"x0":950,"x1":1000},{"count":9,"x0":1000,"x1":1050}]},"mom":{"count":130,"mean":-0.6266862441025296,"median":-1,"stddev":0.9443126057951474,"max":0,"min":0},"yoy":null,"ytd":null},{"month":"2022-07","stats":{"count":3691,"mean":855.335139528583,"median":865,"stddev":69.71894739758197,"max":1026,"min":351,"hist":[{"count":2,"x0":350,"x1":400},{"count":1,"x0":400,"x1":450},{"count":2,"x0":450,"x1":500},{"count":8,"x0":500,"x1":550},{"count":14,"x0":550,"x1":600},{"count":24,"x0":600,"x1":650},{"count":59,"x0":650,"x1":700},{"count":129,"x0":700,"x1":750},{"count":374,"x0":750,"x1":800},{"count":887,"x0":800,"x1":850},{"count":1253,"x0":850,"x1":900},{"count":732,"x0":900,"x1":950},{"count":197,"x0":950,"x1":1000},{"count":9,"x0":1000,"x1":1050}]},"mom":{"count":211,"mean":-0.8318144944055348,"median":0,"stddev":0.1845310457587459,"max":1,"min":0},"yoy":null,"ytd":null},{"month":"2022-06","stats":{"count":3480,"mean":856.1669540229885,"median":865,"stddev":69.53441635182322,"max":1025,"min":351,"hist":[{"count":2,"x0":350,"x1":400},{"count":1,"x0":400,"x1":450},{"count":3,"x0":450,"x1":500},{"count":5,"x0":500,"x1":550},{"count":12,"x0":550,"x1":600},{"count":24,"x0":600,"x1":650},{"count":57,"x0":650,"x1":700},{"count":113,"x0":700,"x1":750},{"count":354,"x0":750,"x1":800},{"count":829,"x0":800,"x1":850},{"count":1171,"x0":850,"x1":900},{"count":716,"x0":900,"x1":950},{"count":183,"x0":950,"x1":1000},{"count":10,"x0":1000,"x1":1050}]},"mom":{"count":390,"mean":-1.9595831938399897,"median":-2,"stddev":0.5375036964698126,"max":1,"min":-25},"yoy":null,"ytd":null},{"month":"2022-05","stats":{"count":3090,"mean":858.1265372168285,"median":867,"stddev":68.99691265535341,"max":1024,"min":376,"hist":[{"count":1,"x0":350,"x1":400},{"count":1,"x0":400,"x1":450},{"count":2,"x0":450,"x1":500},{"count":2,"x0":500,"x1":550},{"count":13,"x0":550,"x1":600},{"count":16,"x0":600,"x1":650},{"count":54,"x0":650,"x1":700},{"count":97,"x0":700,"x1":750},{"count":307,"x0":750,"x1":800},{"count":717,"x0":800,"x1":850},{"count":1045,"x0":850,"x1":900},{"count":651,"x0":900,"x1":950},{"count":174,"x0":950,"x1":1000},{"count":10,"x0":1000,"x1":1050}]},"mom":{"count":349,"mean":-2.266385074306072,"median":-2,"stddev":0.28630967484224357,"max":-4,"min":-60},"yoy":null,"ytd":null},{"month":"2022-04","stats":{"count":2741,"mean":860.3929222911346,"median":869,"stddev":68.71060298051117,"max":1028,"min":436,"hist":[{"count":1,"x0":420,"x1":440},{"count":0,"x0":440,"x1":460},{"count":1,"x0":460,"x1":480},{"count":2,"x0":480,"x1":500},{"count":2,"x0":500,"x1":520},{"count":0,"x0":520,"x1":540},{"count":3,"x0":540,"x1":560},{"count":5,"x0":560,"x1":580},{"count":5,"x0":580,"x1":600},{"count":3,"x0":600,"x1":620},{"count":8,"x0":620,"x1":640},{"count":11,"x0":640,"x1":660},{"count":12,"x0":660,"x1":680},{"count":17,"x0":680,"x1":700},{"count":30,"x0":700,"x1":720},{"count":35,"x0":720,"x1":740},{"count":54,"x0":740,"x1":760},{"count":89,"x0":760,"x1":780},{"count":142,"x0":780,"x1":800},{"count":186,"x0":800,"x1":820},{"count":270,"x0":820,"x1":840},{"count":320,"x0":840,"x1":860},{"count":376,"x0":860,"x1":880},{"count":392,"x0":880,"x1":900},{"count":293,"x0":900,"x1":920},{"count":242,"x0":920,"x1":940},{"count":117,"x0":940,"x1":960},{"count":80,"x0":960,"x1":980},{"count":35,"x0":980,"x1":1000},{"count":8,"x0":1000,"x1":1020},{"count":2,"x0":1020,"x1":1040}]},"mom":{"count":342,"mean":-1.8701039698074737,"median":-2,"stddev":-0.06640779719731427,"max":-7,"min":-27},"yoy":null,"ytd":null},{"month":"2022-03","stats":{"count":2399,"mean":862.2630262609421,"median":871,"stddev":68.77701077770848,"max":1035,"min":463,"hist":[{"count":1,"x0":460,"x1":480},{"count":1,"x0":480,"x1":500},{"count":2,"x0":500,"x1":520},{"count":0,"x0":520,"x1":540},{"count":1,"x0":540,"x1":560},{"count":4,"x0":560,"x1":580},{"count":4,"x0":580,"x1":600},{"count":4,"x0":600,"x1":620},{"count":8,"x0":620,"x1":640},{"count":9,"x0":640,"x1":660},{"count":8,"x0":660,"x1":680},{"count":23,"x0":680,"x1":700},{"count":22,"x0":700,"x1":720},{"count":33,"x0":720,"x1":740},{"count":49,"x0":740,"x1":760},{"count":72,"x0":760,"x1":780},{"count":127,"x0":780,"x1":800},{"count":159,"x0":800,"x1":820},{"count":218,"x0":820,"x1":840},{"count":284,"x0":840,"x1":860},{"count":319,"x0":860,"x1":880},{"count":330,"x0":880,"x1":900},{"count":263,"x0":900,"x1":920},{"count":224,"x0":920,"x1":940},{"count":116,"x0":940,"x1":960},{"count":73,"x0":960,"x1":980},{"count":35,"x0":980,"x1":1000},{"count":8,"x0":1000,"x1":1020},{"count":2,"x0":1020,"x1":1040}]},"mom":{"count":281,"mean":-0.6467943245158949,"median":-1,"stddev":-0.8975252494548869,"max":0,"min":0},"yoy":null,"ytd":null},{"month":"2022-02","stats":{"count":2118,"mean":862.909820585458,"median":872,"stddev":69.67453602716337,"max":1035,"min":463,"hist":[{"count":1,"x0":460,"x1":480},{"count":1,"x0":480,"x1":500},{"count":2,"x0":500,"x1":520},{"count":0,"x0":520,"x1":540},{"count":1,"x0":540,"x1":560},{"count":4,"x0":560,"x1":580},{"count":3,"x0":580,"x1":600},{"count":3,"x0":600,"x1":620},{"count":7,"x0":620,"x1":640},{"count":11,"x0":640,"x1":660},{"count":9,"x0":660,"x1":680},{"count":18,"x0":680,"x1":700},{"count":19,"x0":700,"x1":720},{"count":27,"x0":720,"x1":740},{"count":44,"x0":740,"x1":760},{"count":68,"x0":760,"x1":780},{"count":103,"x0":780,"x1":800},{"count":133,"x0":800,"x1":820},{"count":200,"x0":820,"x1":840},{"count":246,"x0":840,"x1":860},{"count":276,"x0":860,"x1":880},{"count":288,"x0":880,"x1":900},{"count":239,"x0":900,"x1":920},{"count":203,"x0":920,"x1":940},{"count":103,"x0":940,"x1":960},{"count":68,"x0":960,"x1":980},{"count":31,"x0":980,"x1":1000},{"count":8,"x0":1000,"x1":1020},{"count":2,"x0":1020,"x1":1040}]},"mom":{"count":332,"mean":1.1326649303628074,"median":1,"stddev":-1.1071073974214727,"max":0,"min":0},"yoy":null,"ytd":null},{"month":"2022-01","stats":{"count":1786,"mean":861.7771556550952,"median":871,"stddev":70.78164342458484,"max":1035,"min":463,"hist":[{"count":1,"x0":460,"x1":480},{"count":1,"x0":480,"x1":500},{"count":2,"x0":500,"x1":520},{"count":0,"x0":520,"x1":540},{"count":1,"x0":540,"x1":560},{"count":4,"x0":560,"x1":580},{"count":1,"x0":580,"x1":600},{"count":3,"x0":600,"x1":620},{"count":7,"x0":620,"x1":640},{"count":11,"x0":640,"x1":660},{"count":7,"x0":660,"x1":680},{"count":15,"x0":680,"x1":700},{"count":17,"x0":700,"x1":720},{"count":24,"x0":720,"x1":740},{"count":40,"x0":740,"x1":760},{"count":60,"x0":760,"x1":780},{"count":88,"x0":780,"x1":800},{"count":113,"x0":800,"x1":820},{"count":164,"x0":820,"x1":840},{"count":208,"x0":840,"x1":860},{"count":231,"x0":860,"x1":880},{"count":250,"x0":880,"x1":900},{"count":199,"x0":900,"x1":920},{"count":164,"x0":920,"x1":940},{"count":78,"x0":940,"x1":960},{"count":60,"x0":960,"x1":980},{"count":29,"x0":980,"x1":1000},{"count":6,"x0":1000,"x1":1020},{"count":2,"x0":1020,"x1":1040}]},"mom":{"count":-1299,"mean":3.2685657037175133,"median":3,"stddev":-1.9587711775348282,"max":0,"min":436},"yoy":null,"ytd":null},{"month":"2021-12","stats":{"count":3085,"mean":858.5085899513776,"median":868,"stddev":72.74041460211967,"max":1035,"min":27,"hist":[{"count":1,"x0":0,"x1":50},{"count":0,"x0":50,"x1":100},{"count":0,"x0":100,"x1":150},{"count":1,"x0":150,"x1":200},{"count":0,"x0":200,"x1":250},{"count":0,"x0":250,"x1":300},{"count":0,"x0":300,"x1":350},{"count":0,"x0":350,"x1":400},{"count":0,"x0":400,"x1":450},{"count":4,"x0":450,"x1":500},{"count":4,"x0":500,"x1":550},{"count":15,"x0":550,"x1":600},{"count":18,"x0":600,"x1":650},{"count":46,"x0":650,"x1":700},{"count":111,"x0":700,"x1":750},{"count":300,"x0":750,"x1":800},{"count":693,"x0":800,"x1":850},{"count":1020,"x0":850,"x1":900},{"count":676,"x0":900,"x1":950},{"count":185,"x0":950,"x1":1000},{"count":11,"x0":1000,"x1":1050}]},"mom":{"count":38,"mean":-0.35291316644315884,"median":0,"stddev":-0.00823566458342384,"max":0,"min":0},"yoy":null,"ytd":null},{"month":"2021-11","stats":{"count":3047,"mean":858.8615031178208,"median":868,"stddev":72.7486502667031,"max":1035,"min":27,"hist":[{"count":1,"x0":0,"x1":50},{"count":0,"x0":50,"x1":100},{"count":0,"x0":100,"x1":150},{"count":1,"x0":150,"x1":200},{"count":0,"x0":200,"x1":250},{"count":0,"x0":250,"x1":300},{"count":0,"x0":300,"x1":350},{"count":0,"x0":350,"x1":400},{"count":0,"x0":400,"x1":450},{"count":4,"x0":450,"x1":500},{"count":4,"x0":500,"x1":550},{"count":15,"x0":550,"x1":600},{"count":18,"x0":600,"x1":650},{"count":42,"x0":650,"x1":700},{"count":108,"x0":700,"x1":750},{"count":297,"x0":750,"x1":800},{"count":679,"x0":800,"x1":850},{"count":1012,"x0":850,"x1":900},{"count":671,"x0":900,"x1":950},{"count":184,"x0":950,"x1":1000},{"count":11,"x0":1000,"x1":1050}]},"mom":{"count":56,"mean":-0.7312752171842476,"median":-1,"stddev":0.19539677811478384,"max":0,"min":0},"yoy":null,"ytd":null},{"month":"2021-10","stats":{"count":2991,"mean":859.592778335005,"median":869,"stddev":72.55325348858831,"max":1035,"min":27,"hist":[{"count":1,"x0":0,"x1":50},{"count":0,"x0":50,"x1":100},{"count":0,"x0":100,"x1":150},{"count":1,"x0":150,"x1":200},{"count":0,"x0":200,"x1":250},{"count":0,"x0":250,"x1":300},{"count":0,"x0":300,"x1":350},{"count":0,"x0":350,"x1":400},{"count":0,"x0":400,"x1":450},{"count":4,"x0":450,"x1":500},{"count":4,"x0":500,"x1":550},{"count":15,"x0":550,"x1":600},{"count":15,"x0":600,"x1":650},{"count":41,"x0":650,"x1":700},{"count":106,"x0":700,"x1":750},{"count":288,"x0":750,"x1":800},{"count":665,"x0":800,"x1":850},{"count":995,"x0":850,"x1":900},{"count":659,"x0":900,"x1":950},{"count":187,"x0":950,"x1":1000},{"count":10,"x0":1000,"x1":1050}]},"mom":{"count":123,"mean":-0.520192376292016,"median":1,"stddev":0.36143893606799793,"max":-1,"min":0},"yoy":null,"ytd":null},{"month":"2021-09","stats":{"count":2868,"mean":860.1129707112971,"median":868,"stddev":72.19181455252031,"max":1036,"min":27,"hist":[{"count":1,"x0":0,"x1":50},{"count":0,"x0":50,"x1":100},{"count":0,"x0":100,"x1":150},{"count":1,"x0":150,"x1":200},{"count":0,"x0":200,"x1":250},{"count":0,"x0":250,"x1":300},{"count":0,"x0":300,"x1":350},{"count":0,"x0":350,"x1":400},{"count":0,"x0":400,"x1":450},{"count":3,"x0":450,"x1":500},{"count":5,"x0":500,"x1":550},{"count":11,"x0":550,"x1":600},{"count":17,"x0":600,"x1":650},{"count":39,"x0":650,"x1":700},{"count":96,"x0":700,"x1":750},{"count":274,"x0":750,"x1":800},{"count":636,"x0":800,"x1":850},{"count":947,"x0":850,"x1":900},{"count":648,"x0":900,"x1":950},{"count":179,"x0":950,"x1":1000},{"count":11,"x0":1000,"x1":1050}]}}],"players":["82098","15239","5309","29048","5310","59092","95050","27812","96353","59769","98130","54111","110596","8560","8677","25307","35789","85648","101586","135258","116137","102051","8935","140900","42493","103444","50721","95621","107738","62685","123433","3760","8937","13150","30427","70590","97459","101609","125137","48786","68626","101002","103830","8675","42715","49991","130306","4598","44666","121599","226817","4591","49449","34761","53655","85156","25823","79004","135674","32927","93234","115601","11234","82183","8558","30425","42492","78595","97210","157282","3769","4573","177014","39679","68462","81376","135272","228859","13750","68802","106139","118371","121954","122546","130229","56313","58368","84802","120680","48679","64982","91175","45412","66744","74551","209199","8955","36404","66505","102050","121071","125028","128374","38490","46650","60171","73494","83353","95395","115420","178903","182627","49474","85121","122024","135125","190064","8561","29055","84423","88127","92074","101773","179111","95558","117827","226423","24273","43270","81300","82000","105925","140678","12089","34670","43930","98528","122510","8933","38988","75085","97410","130963","207198","47361","59771","77003","83428","85206","103608","162114","188629","198054","53394","59097","76246","97975","162717","132751","29700","55107","66117","94146","119628","173250","142574","8659","8664","35540","36679","41732","50112","53883","57981","97860","124218","156101","178714","213953","68532","91281","92996","66399","91967","103240","141052","3438","16995","49450","52409","110794","116727","120179","124558","130908","142282","177342","190268","245168","37031","82215","119442","120872","122787","123443","125507","131023","122596","131483","147441","182331","206859","211265","4567","53399","53400","77419","78593","78871","109780","142616","234580","250564","47829","53201","74802","95072","186436","82156","93455","124077","137757","170805","49447","67666","125741","8785","17315","73304","79353","117674","138539","141958","146589","171359","184856","123218","125102","157038","175160","198357","66639","78592","108833","124881","222466","34421","39418","42727","75014","104112","108217","121215","122082","148627","165175","90974","94751","138352","151813","167012","180030","42525","50187","74925","97075","108636","123530","127926","131166","147367","158703","180385","222995","238295","60170","110588","116164","116975","119025","137988","140092","149817","243380","74983","109897","111402","167107","186619","35321","4576","44530","55842","82100","101365","101727","125027","131241","137671","167944","51181","120755","122937","131521","138985","142707","183375","222044","237539","3415","3759","8585","43460","58861","59091","59982","67191","71408","82650","102059","105240","142468","149319","155924","168401","189959","196153","205582","228873","77286","93296","106832","135633","140471","235851","46940","53891","75180","108538","119626","155743","180303","180325","42412","66269","75086","111799","125508","128233","137991","140772","180857","184114","8938","65147","103241","119249","122080","140177","175380","180095","186446","219816","46651","125302","142406","149244","152857","160982","175075","180215","188668","190264","60715","103829","108041","126164","135652","140251","140675","142920","151652","159979","174645","176145","189893","190299","201521","63521","65991","82812","91751","94483","96029","103740","105275","121658","136331","150746","160177","171132","192079","193682","59179","67913","74777","89702","108173","124158","127954","178326","180029","205583","244987","3436","8662","74588","85509","92080","107143","109284","116820","120114","136181","142489","143632","151868","176994","202384","202849","219008","46729","57672","65978","73122","88603","94389","98582","111524","135568","147003","164844","173373","219357","30302","38638","46913","50011","50186","51182","86845","92358","104429","111694","173711","182156","190869","34671","52639","82099","87508","91110","98392","115590","126531","139980","142059","186691","212628","215761","85713","118492","124913","129864","130114","146024","173530","181877","189502","204694","218666","236819","5304","8934","51216","111533","115355","130046","138614","145501","145522","156886","160124","175163","207907","91177","99501","123136","137598","144098","145899","161085","170821","173435","173698","177478","187261","188063","190364","203363","39767","57361","116704","142325","181287","181582","206706","207181","207237","38492","59178","91011","101528","109118","120966","121506","146488","164464","173457","191008","38473","38474","122392","124785","125071","126925","127956","142481","143089","180074","181297","185731","187177","192815","204964","50072","77710","85347","102159","145524","171870","173079","174428","181315","191793","203896","207032","221107","29051","75234","104488","119843","124349","127442","130654","148027","157270","164488","165554","185052","212788","239823","36405","82649","103609","118826","124839","125287","129782","131751","139121","160060","161595","164467","173575","205063","210734","216262","224114","224348","139387","3429","8663","8931","44785","61428","66917","73631","76158","79463","141505","150035","171030","172521","176204","182634","184882","185307","3758","8666","111785","141048","153735","166426","177391","180651","180730","196661","209700","214354","222100","5308","46880","51856","77175","114989","122042","133397","142386","160473","163314","173038","185053","185907","194415","201853","205535","217524","8575","29699","47237","94300","130193","146965","159857","165774","172196","173301","175083","177251","180962","186512","187296","188345","209498","226618","229074","249342","8596","77903","95338","103696","103717","109131","127980","128023","134899","135821","150021","161221","204340","209093","215463","8963","68052","98543","108503","119676","133921","135689","135704","137175","145606","153896","168133","205991","210240","214236","215031","221913","227439","42494","53547","61122","92861","95339","96132","102748","103194","104136","123652","135555","142540","146132","158390","176349","178097","180108","215636","219221","224012","225774","229072","8670","49448","73841","97489","121981","123629","134419","145425","148508","161434","166314","175219","182029","193535","208883","226140","8584","48883","79222","80216","89483","101610","107131","121143","124189","128126","132307","144445","146576","159852","160653","175329","182211","188473","191185","191540","195397","204818","216761","222609","229037","242205","66298","90372","108043","119133","119227","119993","122379","131424","136557","145340","160917","170718","172177","172578","174221","180914","181873","189680","228679","52060","131701","134429","134549","136748","140250","165328","186986","200722","209081","209556","223648","231072","47035","50428","84492","103242","116818","127129","130015","132693","137966","183765","188413","189086","215616","241085","242360","242890","53147","87273","102857","104335","130397","131213","137595","139319","145276","147476","147633","171138","176200","177072","183239","198157","202008","204345","204843","206475","212680","31802","54614","70899","91153","109990","114387","117858","118557","124458","124468","125230","129107","129323","134807","139369","140877","156378","172693","179128","184651","186071","187881","205061","214639","215387","217726","227358","103330","116207","122087","130183","131524","135754","139286","140775","141756","148822","149047","164309","169273","174046","181918","182271","202401","208966","220238","229710","239360","43269","83902","84231","90213","93459","108475","114927","137404","141275","146868","156258","160379","182368","184476","196896","198751","199308","203976","209225","210298","218523","223955","226457","60954","73301","80510","88299","106946","108874","119564","121663","131700","152978","202532","214402","216946","224909","232529","238051","58826","101135","157054","176569","176702","181171","189233","200966","204744","215316","216400","185057","53401","75970","78792","113500","116043","131544","135129","160065","178972","218127","223906","65149","89281","93045","125839","137171","140176","161062","174107","174283","175725","176006","185056","197773","204847","205076","142225","60168","68995","77981","103940","106431","117411","132495","135157","145273","150349","165031","174731","176056","176211","176285","179679","180607","182011","186072","189271","191495","193940","205940","224451","70280","107811","113195","125743","126191","131276","135697","141369","161593","166659","175156","180858","182224","184758","200625","205453","207859","207902","214775","218586","230567","3421","50329","53204","77547","85204","96628","125847","149774","172997","173189","174729","176050","177393","184819","187159","198579","205052","205225","213271","213376","3767","38495","39677","106469","111793","118305","126750","146853","175783","179640","188414","189919","222127","244061","3439","48884","76929","134303","144953","164352","171292","171507","173892","178975","185853","190325","192283","196124","217544","70595","91123","103612","112701","116051","125303","126968","139203","143453","148668","149450","151814","170719","172263","175997","179127","179376","185366","186699","188904","197514","204844","208300","212005","215072","217512","229590","25235","77357","84295","107862","120418","127658","132267","141549","142322","157453","169802","170806","173085","173537","181350","181352","187495","187543","193978","194497","201451","243546","102383","116104","120333","124676","137983","160175","165731","168317","179476","180650","184595","203373","208527","209267","214446","218057","218408","219442","228763","238427","84276","90308","123771","139231","148651","153578","160067","171207","179775","180721","180757","186481","202426","3752","30939","45160","109523","119460","135616","137911","144473","152051","186903","187382","209343","212848","214846","228988","229529","233416","77385","82641","107285","126168","136184","160071","172831","173703","180277","188914","189739","200478","201752","204196","241606","155026","179873","3418","64389","76337","107580","113572","122023","129991","138946","175162","180788","181004","203061","203347","212772","221676","239543","60040","146423","152311","155095","169218","180615","200721","204411","204855","206217","211944","217283","219316","219798","239716","35097","40048","42417","108018","115574","122031","127237","129339","134967","144667","148604","170599","176045","178109","181121","182254","184772","189290","191555","201221","206114","215920","38478","56708","103190","122188","122580","123298","126240","128363","130396","146581","165332","167582","173538","179367","196319","200865","202410","204737","205210","205371","206070","211301","214453","215901","216022","217813","219062","221091","231757","13175","99483","107525","109656","134305","135962","136100","168004","188978","189751","213200","216200","228411","231169","245638","117754","160911","162365","173037","180658","180734","180779","181236","185174","190282","210141","213395","213490","213702","219219","234146","238736","51388","110443","119629","130736","133867","134546","135678","148623","168099","170630","182277","187658","197928","202702","202931","204814","205207","206119","209198","227351","232501","76644","103188","108384","123758","133696","135390","135858","141586","158127","164738","165242","173944","173952","174228","176172","176272","177596","190283","205227","215237","218075","219799","221392","232659","121554","1582","124844","127674","140077","157433","164374","166607","175410","182030","186256","187383","193023","199887","203485","205934","206072","213463","218723","228319","232463","238261","4560","71710","131174","140807","144351","155608","164773","172075","172540","173265","175308","181695","184551","188867","204600","213144","215758","216035","216317","220144","220794","221104","232735","107174","142856","166138","174745","180886","182878","187590","191682","208984","232591","73529","116728","178325","180327","180720","182797","183617","183723","187653","206998","213917","221294","225472","34954","57373","107931","110243","162016","162267","171363","175811","178046","179563","180930","183435","187977","189154","209221","215462","228886","229120","233595","241156","51855","76754","107989","108424","120881","122218","136477","145484","150344","157706","168031","176154","184984","185983","189449","189727","189894","204966","210755","214789","216796","219840","237031","58694","64703","81403","103041","118980","119730","129948","131758","137905","149650","155417","175388","186452","187512","190602","200252","201250","203569","203857","206480","213925","218471","229205","231410","232371","121240","70901","75285","133175","139924","169483","182803","186848","188728","197985","199092","201779","211251","213388","219980","224116","226432","233539","237107","242229","95581","97595","126224","133740","139371","140592","142411","163274","177783","178114","202745","209156","210234","214088","218256","224082","229803","241415","8599","99530","138161","161589","173003","183896","192462","206406","210995","213326","216288","218073","221901","230566","138379","155612","163358","171151","173000","173120","180383","182272","182498","197988","213458","214405","218123","219235","224412","232655","232828","234809","249011","108925","123975","127682","135737","147364","158216","177482","181700","184862","187979","190582","225212","250203","103611","130767","136685","169280","172262","178968","186597","195735","198666","200855","214092","216210","218046","219029","220439","221990","81656","112945","121097","139112","153357","180726","184979","194440","195316","203647","209021","215765","218473","224471","111514","111699","47918","124466","142850","145486","161834","162307","171294","178978","185051","194866","198272","205488","211026","214135","219945","220199","248067","91819","96423","120767","139780","162484","171293","174396","174486","175231","178606","186791","190460","199307","202863","206213","206241","207228","208526","212505","221022","250694","101587","117948","125039","130762","149973","151170","172703","179686","180324","203189","203351","205593","218710","103822","125806","144242","165369","167726","174136","175427","179643","181507","190610","200754","204870","205600","212992","218763","225891","227607","238409","241471","51567","80398","94891","121816","135571","150122","161992","185091","186590","195140","205346","206708","207436","219835","225561","239034","8966","42832","56707","75611","81508","147723","149583","167048","168576","171395","175064","182017","185527","200923","202576","202580","204113","213855","217105","217551","221532","229476","242888","39578","79934","84193","95092","112174","114522","122648","131221","166131","173383","176298","183456","184692","197649","202378","205572","205826","208805","209916","217025","218052","220338","222439","234052","95922","131859","139464","142568","155816","176149","182047","182868","200944","203376","206077","211754","215046","219069","223763","231126","243159","63165","137054","118072","161239","174398","175510","178971","193177","203259","206594","217549","223299","224128","93601","130014","117071","122214","132766","140078","146861","161217","161310","171331","180860","181261","181302","186795","188990","192011","193979","199882","205075","210840","226225","238958","102610","107323","108569","115063","119286","124722","132752","145832","172351","174421","175052","176287","177807","179573","184695","189749","200965","201449","206926","215452","218244","221340","230704","235100","237079","93971","121141","140659","142940","146696","167244","171298","176193","192084","198116","207344","209511","217109","226934","231322","232681","236003","239843","247073","82769","151671","175018","178737","183450","189547","191802","194836","196063","201220","204956","217210","218134","229442","242350","31701","102567","138765","147610","172219","172692","173005","173050","181884","183224","200247","212365","221261","224458","230024","230768","232736","103547","185373","206376","79003","109679","124140","134639","135215","156010","178654","187019","189476","192195","213779","219586","229290","242078","122869","147716","173263","173406","185327","186303","186598","190956","206577","214423","218469","218621","220507","234808","247517","148052","152855","176151","185376","189016","206784","207066","209210","225657","227402","107428","122255","128111","131835","131873","139917","144410","147380","148532","160385","166457","172751","184759","200245","207461","210675","210996","215184","216865","218049","225792","226057","98715","124429","173168","189450","194849","205292","210741","213785","214149","219740","220523","226844","227091","230223","237903","242063","85641","104661","123032","137192","139209","170549","173975","181316","183419","187319","189152","221727","242672","242771","3432","107858","126001","127871","157900","169725","174771","176346","180423","182256","184419","199688","202851","208842","215153","231385","237272","243192","95670","142683","165048","166525","167767","180007","181395","186995","188720","206923","210728","216910","225310","226708","228430","247564","64234","107860","106355","108254","194397","204935","205352","205555","206607","210242","211463","212112","218663","235754","243651","89044","150140","171385","175336","183696","185080","187794","193715","211894","217064","222863","247410","138081","10782","107524","121837","138723","156033","161355","173185","175660","175805","188368","191196","203159","210428","216697","231891","239308","156259","54615","76338","102139","103610","103833","103862","148015","160084","161347","180234","180792","181622","181723","197987","205584","212576","216080","221447","229802","242891","246251","158379","161363","191093","194502","195151","199520","200627","202376","212692","220285","222443","228805","229450","229620","238735","241486","229655","124283","159699","169304","175188","188675","204527","205111","218583","220101","45159","38476","47917","107273","110934","128679","148665","176695","181584","201687","202534","204979","206925","209147","213218","220293","222903","226763","175392","190230","112109","130655","135824","152258","154631","157319","161308","199408","204810","232834","236350","242663","245199","174285","182450","111922","121790","130458","151200","153710","165533","170929","172738","174152","185714","193422","196120","209244","210069","211643","224746","103947","104318","134936","147500","150219","151124","172885","178515","186257","216420","247052","180210","142994","146989","180010","182379","200239","213981","221496","228603","235375","123116","136894","142176","149462","172349","187373","188436","209051","219829","223640","227610","238184","245193","1187","163266","179313","189575","190586","190604","191526","198117","213692","216771","218883","220959","221860","232725","234564","242177","250670","210542","52311","53892","120848","149307","173275","192275","209715","211817","228667","229760","179433","97335","181372","201858","206130","212480","216286","217498","217947","235001","47148","103239","131841","137501","185408","187378","201507","202218","218266","228954","241073","123153","172858","183381","184696","187028","201468","204954","214422","217377","229478","103955","160935","164484","175303","219339","221867","223018","232127","235378","245641","143295","57375","66512","109733","127680","155851","178439","188591","188593","188991","189682","193847","211101","230410","236996","247683","248050","250529","8976","111996","177278","186595","204186","205812","213923","223951","244451","134935","119231","143361","170899","172392","174135","182282","189610","201685","203645","205016","209560","216034","216064","229632","247201","248408","137990","144257","164755","175098","178438","180737","186836","188435","197668","201147","209558","211453","215877","220647","76066","40047","166101","187885","201737","211729","218061","218772","233857","65479","131757","138218","142695","168398","169774","171327","173702","176059","196499","140910","149415","212397","216398","224744","224876","227872","235413","177352","183826","191797","201496","215640","219374","225441","232351","234797","26585","162264","135557","178894","180061","181356","193134","196819","201850","211875","216626","225434","143439","99518","125512","170598","204930","209553","220515","241515","25847","131848","140195","157975","166485","172896","218992","233931","237140","238204","108454","215919","75041","113409","135471","148003","178502","196820","197921","216867","227150","229436","150348","175499","181741","199881","209739","211883","220864","222034","229482","230136","203676","138551","160190","169772","198310","201193","201656","218773","231991","222711","130172","188267","188271","219496","127137","145510","162668","209653","219450","229106","206484","50111","150114","181718","184706","187864","193183","242638","145975","108946","124549","152094","176703","203236","212835","215309","216699","219368","205586","61247","121355","140070","151655","171136","176566","201306","154082","205978","216919","131435","139417","173899","187006","201859","227544","230137","231511","64704","170770","131910","189728","193960","205325","209395","215764","225493","132180","171717","178509","183544","185189","208405","212803","216151","249930","159602","190112","192730","209270","210307","143166","169756","175333","187475","216443","221339","232167","235824","186535","214623","226011","231700","189646","78855","96990","116290","160961","167580","181619","181769","233986","214779","112946","155546","163317","176564","232279","184656","146489","173446","173768","177369","236483","241480","124791","127372","157434","203367","203413","224809","229557","245549","246942","108333","76668","181810","192385","225226","226207","169917","214408","215770","226099","237644","244060","188442","136855","217111","225439","231400","238733","249474","107746","146181","181856","207304","209509","216543","218996","230318","232675","243388","250687","114823","164750","174576","177370","186900","206337","213811","221381","225318","226262","236445","188440","121543","126539","174061","174927","194548","200618","221351","140909","181126","181823","194270","212400","214584","229302","57984","181854","180611","185533","204507","210969","228675","231924","152705","145495","207020","224191","237703","248245","135534","213325","232728","234553","237789","194544","221999","231698","214084","152011","190253","225101","232458","134250","229715","189011","213152","230788","131815","139385","161467","191881","214514","218909","218921","248416","158214","133538","168217","126060","163811","210546","198287","216585","223463","247898","243378","139384","166608","182455","183373","209949","123237","218344","186906","192725","211727","218063","202881","227346","151121","200454","224413","240525","245008","90104","215651","244882","244894","198543","188300","229044","237005","242232","191798","78156","230111","176489","219437","177166","195124","200249","213826","241979","244542","141582","154818","241791","107488","140389","224565","223977","178483","186985","212672","219697","160073","179304","217194","221498","228170","243367","8909","170417","190585","206342","209250","243186","151165","206121","200248","210155","221851","247232","247270","184323","214003","218067","218243","227987","246947","174058","188427","104147","211143","213915","187513","195341","232666","183114","220960","231581","247940","188937","143455","184701","204257","217237","239368","202018","147414","193831","185199","232302","4580","172355","200455","226622","196364","248780","204412","199075","238426","144241","209954","111902","221869","93970","191800","205443","42575","225031","228140","242695","244835","205136","47646","211274","219574","247189","224238","181578","217243","193539","241478","216895","142302","153561","191621","214094","232404","229876","230306","189699","187823","219242","130081","160782","173424","190550","124979","220115","161050","223957","229356","142948","245082","221499","172175","195319","215047","244102","81840","203926","219453","227609","238957","249000","109730","212688","184921","232649","248499","160892","189367","208879","251896","214427","215596","211247","183478","186334","192295","154819","186454","189477","206476","221256","245711","246506","173014","94092","191712","143846","188590","221643","224400","192543","228798","238667","200922","79221","149688","233527","178670","231225","198577","214881","249645","146854","194974","113901","239265","200486","228863","172350","206580","221540","8939","155533","66270","239954","246751","220648","247064","202771","175467","151973","128869","223298","251432","210568","214899","206057","242192","40046","180011","207887","246586","190549","210710","238593","210986","227427","222343","233221","162040","228769","250556","204750","178893","184827","246488","211877","144485","205302","225481","202759","222620","234244","118983","213316","150644","222251","216314","186031","188263","141581","180019","208444","157115","179378","229373","119565","214941","189165","183823"]}}